sacrebleu/__init__.py
sacrebleu/__main__.py
sacrebleu/compat.py
sacrebleu/py.typed
sacrebleu/sacrebleu.py
sacrebleu/significance.py
sacrebleu/utils.py
sacrebleu/version.py
sacrebleu/dataset/__init__.py
sacrebleu/dataset/__main__.py
sacrebleu/dataset/base.py
sacrebleu/dataset/fake_sgml.py
sacrebleu/dataset/iwslt_xml.py
sacrebleu/dataset/plain_text.py
sacrebleu/dataset/tsv.py
sacrebleu/dataset/wmt_xml.py
sacrebleu/metrics/__init__.py
sacrebleu/metrics/base.py
sacrebleu/metrics/bleu.py
sacrebleu/metrics/chrf.py
sacrebleu/metrics/helpers.py
sacrebleu/metrics/lib_ter.py
sacrebleu/metrics/ter.py
sacrebleu/tokenizers/__init__.py
sacrebleu/tokenizers/tokenizer_13a.py
sacrebleu/tokenizers/tokenizer_base.py
sacrebleu/tokenizers/tokenizer_char.py
sacrebleu/tokenizers/tokenizer_intl.py
sacrebleu/tokenizers/tokenizer_ja_mecab.py
sacrebleu/tokenizers/tokenizer_ko_mecab.py
sacrebleu/tokenizers/tokenizer_none.py
sacrebleu/tokenizers/tokenizer_re.py
sacrebleu/tokenizers/tokenizer_spm.py
sacrebleu/tokenizers/tokenizer_ter.py
sacrebleu/tokenizers/tokenizer_zh.py
sacrebleu-2.4.3.dist-info/LICENSE.txt
sacrebleu-2.4.3.dist-info/METADATA
sacrebleu-2.4.3.dist-info/WHEEL
sacrebleu-2.4.3.dist-info/entry_points.txt
sacrebleu-2.4.3.dist-info/top_level.txt
sacrebleu-2.4.3.dist-info/RECORD
