Metadata-Version: 2.1
Name: sacrebleu
Version: 2.4.3
Summary: Hassle-free computation of shareable, comparable, and reproducible BLEU, chrF, and TER scores
Author-email: Matt Post <post@cs.jhu.edu>
Maintainer-email: Matt Post <post@cs.jhu.edu>
License:                                  Apache License
Project-URL: Repository, https://github.com/mjpost/sacrebleu
Keywords: machine translation,evaluation,NLP,natural language processing,computational linguistics
Classifier: Development Status :: 5 - Production/Stable
Classifier: Intended Audience :: Developers
Classifier: Intended Audience :: Science/Research
Classifier: Topic :: Scientific/Engineering
Classifier: Topic :: Scientific/Engineering :: Artificial Intelligence
Classifier: Topic :: Text Processing
Classifier: License :: OSI Approved :: Apache Software License
Classifier: Operating System :: POSIX
Classifier: Operating System :: MacOS :: MacOS X
Classifier: Operating System :: Microsoft :: Windows
Classifier: Programming Language :: Python :: 3 :: Only
Classifier: Typing :: Typed
Requires-Python: >=3.8
License-File: LICENSE.txt
Requires-Dist: portalocker
Requires-Dist: regex
Requires-Dist: tabulate>=0.8.9
Requires-Dist: numpy>=1.17
Requires-Dist: colorama
Requires-Dist: lxml
Provides-Extra: dev
Requires-Dist: wheel; extra == "dev"
Requires-Dist: pytest; extra == "dev"
Requires-Dist: mypy; extra == "dev"
Requires-Dist: types-tabulate; extra == "dev"
Requires-Dist: lxml-stubs; extra == "dev"
Requires-Dist: setuptools; extra == "dev"
Provides-Extra: ja
Requires-Dist: mecab-python3<2.0.0,>=1.0.9; extra == "ja"
Requires-Dist: ipadic<2.0,>=1.0; extra == "ja"
Provides-Extra: ko
Requires-Dist: mecab-ko<=1.0.1,>=1.0.0; extra == "ko"
Requires-Dist: mecab-ko-dic<2.0,>=1.0; extra == "ko"
